SM24b8vin/_24b8vin_data.py
SM24b8vin/__init__.py
sm24b8vin-1.0.1.dist-info/METADATA
sm24b8vin-1.0.1.dist-info/WHEEL
sm24b8vin-1.0.1.dist-info/top_level.txt
sm24b8vin-1.0.1.dist-info/RECORD
